LICENSE
MANIFEST.in
README.rst
setup.py
keputils/__init__.py
keputils/distributions.py
keputils/errors.py
keputils/kicutils.py
keputils/koiutils.py
keputils/lc.py
keputils/utils.py
keputils.egg-info/PKG-INFO
keputils.egg-info/SOURCES.txt
keputils.egg-info/dependency_links.txt
keputils.egg-info/not-zip-safe
keputils.egg-info/requires.txt
keputils.egg-info/top_level.txt
scripts/koiquery