Metadata-Version: 1.1
Name: keputils
Version: 0.2.1
Summary: Basic module for interaction with KOI and Kepler-stellar tables.
Home-page: https://github.com/timothydmorton/keputils
Author: Timothy D. Morton
Author-email: tim.morton@gmail.com
License: UNKNOWN
Platform: UNKNOWN
Classifier: Development Status :: 3 - Alpha
Classifier: Intended Audience :: Science/Research
Classifier: Operating System :: OS Independent
Classifier: Programming Language :: Python
Classifier: Topic :: Scientific/Engineering
Classifier: Topic :: Scientific/Engineering :: Astronomy
